ruffruffs
